lme/__init__.py
lme/prices.py
lme-0.5.2.dist-info/LICENSE
lme-0.5.2.dist-info/METADATA
lme-0.5.2.dist-info/WHEEL
lme-0.5.2.dist-info/top_level.txt
lme-0.5.2.dist-info/RECORD
