Metadata-Version: 2.1
Name: lme
Version: 0.5.2
Summary: Cotação London Metal Exchange
Home-page: https://github.com/tiagocordeiro/lme
Author: Tiago Cordeiro
Author-email: tiago@mulhergorila.com
License: MIT
Classifier: Development Status :: 4 - Beta
Classifier: Environment :: Console
Classifier: Intended Audience :: Developers
Classifier: License :: OSI Approved :: MIT License
Classifier: Natural Language :: Portuguese (Brazilian)
Classifier: Operating System :: OS Independent
Classifier: Programming Language :: Python
Classifier: Programming Language :: Python :: 3
Classifier: Framework :: Paste
License-File: LICENSE
Requires-Dist: requests
Requires-Dist: rich
